CHANGES.txt
MANIFEST.in
requirements.txt
setup.py
HotCIDR.egg-info/PKG-INFO
HotCIDR.egg-info/SOURCES.txt
HotCIDR.egg-info/dependency_links.txt
HotCIDR.egg-info/requires.txt
HotCIDR.egg-info/top_level.txt
bin/hc-apply
bin/hc-audit
bin/hc-deleteexpired
bin/hc-fetch
bin/hc-validate
hotcidr/__init__.py
hotcidr/apply.py
hotcidr/audit.py
hotcidr/deleteexpired.py
hotcidr/fetch.py
hotcidr/notifyemail.py
hotcidr/ports.py
hotcidr/state.py
hotcidr/util.py
hotcidr/validation.py
hotcidr.egg-info/SOURCES.txt
hotcidr/test/__init__.py
hotcidr/test/test_expiration.py
hotcidr/test/test_validation.py