Metadata-Version: 1.0
Name: hotcidr
Version: 0.1.0
Summary: Firewall rule management and automation tools
Home-page: https://github.com/ViaSat/hotcidr
Author: Justin Bass, James Kwan, Austin Solomon
Author-email: stephan.kemper@viasat.com
License: Apache License 2.0
Platform: UNKNOWN
